pyconvertio/__init__.py
pyconvertio/pyconvertio.py
pyconvertio-0.1.0.dist-info/METADATA
pyconvertio-0.1.0.dist-info/WHEEL
pyconvertio-0.1.0.dist-info/top_level.txt
pyconvertio-0.1.0.dist-info/RECORD
